cactuscat/__init__.py
cactuscat/_cactuscat.cpython-311-x86_64-linux-gnu.so
cactuscat/application.py
cactuscat/apputils/analyzer.py
cactuscat/apputils/console.py
cactuscat/apputils/guard.py
cactuscat/apputils/metadata.py
cactuscat/apputils/serializer.py
cactuscat/apputils/shell.py
cactuscat/apputils/state.py
cactuscat/apputils/updater.py
cactuscat/bin/rcedit-x64.exe
cactuscat/bin/windows-utf8.manifest
cactuscat/ccat/index.js
cactuscat/ccat/package.json
cactuscat/cli.py
cactuscat/commands/android.py
cactuscat/commands/doctor.py
cactuscat/commands/engine.py
cactuscat/commands/harvest.py
cactuscat/commands/init.py
cactuscat/commands/install.py
cactuscat/commands/package.py
cactuscat/commands/plugin.py
cactuscat/commands/run.py
cactuscat/commands/ts_gen.py
cactuscat/commands/workflow.py
cactuscat/engines/__init__.py
cactuscat/engines/chrome.py
cactuscat/engines/native.py
cactuscat/inspector.py
cactuscat/menu.py
cactuscat/plugins.py
cactuscat/router.py
cactuscat/shortcuts.py
cactuscat-0.1.9.dist-info/METADATA
cactuscat-0.1.9.dist-info/WHEEL
cactuscat-0.1.9.dist-info/entry_points.txt
cactuscat.libs/libEGL-875ecbb2.so.1
cactuscat.libs/libGLX-16fc8a37.so.0
cactuscat.libs/libGLdispatch-ca01a911.so.0
cactuscat.libs/libX11-xcb-966fc171.so.1
cactuscat.libs/libXau-8040da3f.so.6
cactuscat.libs/libXcomposite-675c78d8.so.1
cactuscat.libs/libXcursor-09bd5941.so.1
cactuscat.libs/libXdamage-6ff910fb.so.1
cactuscat.libs/libXdmcp-667d97d6.so.6
cactuscat.libs/libXfixes-89e5897f.so.3
cactuscat.libs/libXi-a51348c9.so.6
cactuscat.libs/libXinerama-dceff724.so.1
cactuscat.libs/libXrandr-bc6120a7.so.2
cactuscat.libs/libXtst-b2364489.so.6
cactuscat.libs/libatk-1-d312f3db.0.so.0
cactuscat.libs/libatk-bridge-2-366fcd2f.0.so.0
cactuscat.libs/libatspi-4af877d2.so.0
cactuscat.libs/libblkid-9d1afba3.so.1
cactuscat.libs/libbrotlicommon-a91ead09.so.1
cactuscat.libs/libbrotlidec-64d8a501.so.1
cactuscat.libs/libbsd-e86cd4f0.so.0
cactuscat.libs/libbz2-218c4abd.so.1.0
cactuscat.libs/libcairo-3144bd59.so.2
cactuscat.libs/libcairo-gobject-61b4b6cb.so.2
cactuscat.libs/libcap-0e62ac39.so.2
cactuscat-0.1.9.dist-info/RECORD
