Metadata-Version: 2.4
Name: cactuscat
Version: 0.1.9
Classifier: Programming Language :: Rust
Classifier: Programming Language :: Python :: Implementation :: CPython
Classifier: Programming Language :: Python :: Implementation :: PyPy
Classifier: License :: OSI Approved :: MIT License
Classifier: Operating System :: Microsoft :: Windows
Classifier: Operating System :: POSIX :: Linux
Classifier: Operating System :: MacOS :: MacOS X
Requires-Dist: rich>=13.0.0
Requires-Dist: watchfiles>=0.20.0
Requires-Dist: bsdiff4>=1.2.4
Requires-Dist: psutil>=5.9.0
Requires-Dist: cryptography>=42.0.0
Requires-Dist: metaedit>=0.1.0
Summary: The ultra-fast, Rust-powered bridge between Python and the Web.
Keywords: webview,rust,python,desktop,hybrid,rpc
Author-email: Ghua8088 <ghua8088.contact@gmail.com>
License: MIT
Requires-Python: >=3.7
Project-URL: Documentation, https://cactuscat.io
Project-URL: Homepage, https://github.com/cactuscat-org/cactuscat
Project-URL: Repository, https://github.com/cactuscat-org/cactuscat
